Metadata-Version: 2.1
Name: scene-text
Version: 0.2.2
Summary: Finding text in photos
Home-page: https://github.com/gtsoukas/scene_text
Author: Georgios Tsoukas
Author-email: georgios@dict.gr
License: UNKNOWN
Keywords: scene text detection recognition
Platform: UNKNOWN
Classifier: Programming Language :: Python :: 3
Classifier: License :: OSI Approved :: MIT License
Classifier: Operating System :: POSIX :: Linux
Requires-Python: >=3
